[
    {
        "subject": "http://dbpedia.org/resource/Bruno_Fonseca",
        "predicate": "http://dbpedia.org/ontology/wikiPageWikiLink",
        "object": "http://dbpedia.org/resource/Carrara"
    },
    {
        "subject": "http://dbpedia.org/resource/Bruno_Fonseca",
        "predicate": "http://dbpedia.org/ontology/wikiPageWikiLink",
        "object": "http://dbpedia.org/resource/Valencia"
    },
    {
        "subject": "http://dbpedia.org/resource/Bruno_Fonseca",
        "predicate": "http://dbpedia.org/ontology/wikiPageWikiLink",
        "object": "http://dbpedia.org/resource/Category:1959_births"
    },
    {
        "subject": "http://dbpedia.org/resource/Bruno_Fonseca",
        "predicate": "http://dbpedia.org/ontology/wikiPageWikiLink",
        "object": "http://dbpedia.org/resource/Category:Living_people"
    },
    {
        "subject": "http://dbpedia.org/resource/Bruno_Fonseca",
        "predicate": "http://dbpedia.org/ontology/wikiPageWikiLink",
        "object": "http://dbpedia.org/resource/Corcoran_Gallery_of_Art"
    },
    {
        "subject": "http://dbpedia.org/resource/Bruno_Fonseca",
        "predicate": "http://dbpedia.org/ontology/wikiPageWikiLink",
        "object": "http://dbpedia.org/resource/Category:Hispanic_and_Latino_American_artists"
    },
    {
        "subject": "http://dbpedia.org/resource/Bruno_Fonseca",
        "predicate": "http://dbpedia.org/ontology/wikiPageWikiLink",
        "object": "http://dbpedia.org/resource/Gonzalo_Fonseca"
    },
    {
        "subject": "http://dbpedia.org/resource/Bruno_Fonseca",
        "predicate": "http://dbpedia.org/ontology/wikiPageWikiLink",
        "object": "http://dbpedia.org/resource/Museum_of_Modern_Art"
    },
    {
        "subject": "http://dbpedia.org/resource/Bruno_Fonseca",
        "predicate": "http://dbpedia.org/ontology/wikiPageWikiLink",
        "object": "http://dbpedia.org/resource/Manhattan"
    },
    {
        "subject": "http://dbpedia.org/resource/Bruno_Fonseca",
        "predicate": "http://dbpedia.org/ontology/wikiPageWikiLink",
        "object": "http://dbpedia.org/resource/SoHo,_Manhattan"
    },
    {
        "subject": "http://dbpedia.org/resource/Bruno_Fonseca",
        "predicate": "http://dbpedia.org/ontology/wikiPageWikiLink",
        "object": "http://dbpedia.org/resource/Barcelona"
    },
    {
        "subject": "http://dbpedia.org/resource/Bruno_Fonseca",
        "predicate": "http://dbpedia.org/ontology/wikiPageWikiLink",
        "object": "http://dbpedia.org/resource/Category:20th-century_American_male_artists"
    },
    {
        "subject": "http://dbpedia.org/resource/Bruno_Fonseca",
        "predicate": "http://dbpedia.org/ontology/wikiPageWikiLink",
        "object": "http://dbpedia.org/resource/Category:20th-century_American_painters"
    },
    {
        "subject": "http://dbpedia.org/resource/Bruno_Fonseca",
        "predicate": "http://dbpedia.org/ontology/wikiPageWikiLink",
        "object": "http://dbpedia.org/resource/Category:American_artists"
    },
    {
        "subject": "http://dbpedia.org/resource/Bruno_Fonseca",
        "predicate": "http://dbpedia.org/ontology/wikiPageWikiLink",
        "object": "http://dbpedia.org/resource/Category:American_male_painters"
    },
    {
        "subject": "http://dbpedia.org/resource/Bruno_Fonseca",
        "predicate": "http://dbpedia.org/ontology/wikiPageWikiLink",
        "object": "http://dbpedia.org/resource/Bruno_Fonseca"
    },
    {
        "subject": "http://dbpedia.org/resource/Bruno_Fonseca",
        "predicate": "http://dbpedia.org/ontology/wikiPageWikiLink",
        "object": "http://dbpedia.org/resource/Category:American_people_of_Uruguayan_descent"
    },
    {
        "subject": "http://dbpedia.org/resource/Bruno_Fonseca",
        "predicate": "http://dbpedia.org/ontology/wikiPageWikiLink",
        "object": "http://dbpedia.org/resource/Tuscany"
    },
    {
        "subject": "http://dbpedia.org/resource/Bruno_Fonseca",
        "predicate": "http://dbpedia.org/ontology/wikiPageWikiLink",
        "object": "http://dbpedia.org/resource/Washington,_DC"
    },
    {
        "subject": "http://dbpedia.org/resource/Bruno_Fonseca",
        "predicate": "http://dbpedia.org/ontology/wikiPageWikiLink",
        "object": "http://dbpedia.org/resource/Whitney_Museum_of_American_Art"
    },
    {
        "subject": "http://dbpedia.org/resource/Bruno_Fonseca",
        "predicate": "http://dbpedia.org/ontology/wikiPageWikiLink",
        "object": "http://dbpedia.org/resource/Isabel_Fonseca"
    },
    {
        "subject": "http://dbpedia.org/resource/Bruno_Fonseca",
        "predicate": "http://dbpedia.org/ontology/wikiPageWikiLink",
        "object": "http://dbpedia.org/resource/East_Village,_Manhattan"
    },
    {
        "subject": "http://dbpedia.org/resource/Bruno_Fonseca",
        "predicate": "http://dbpedia.org/ontology/wikiPageWikiLink",
        "object": "http://dbpedia.org/resource/Paris"
    },
    {
        "subject": "http://dbpedia.org/resource/Bruno_Fonseca",
        "predicate": "http://dbpedia.org/ontology/wikiPageWikiLink",
        "object": "http://dbpedia.org/resource/Smithsonian"
    },
    {
        "subject": "http://dbpedia.org/resource/Bruno_Fonseca",
        "predicate": "http://dbpedia.org/ontology/wikiPageWikiLink",
        "object": "http://dbpedia.org/resource/Category:21st-century_American_painters"
    },
    {
        "subject": "http://dbpedia.org/resource/Bruno_Fonseca",
        "predicate": "http://dbpedia.org/ontology/wikiPageWikiLink",
        "object": "http://dbpedia.org/resource/Category:People_from_Greenwich_Village"
    },
    {
        "subject": "http://dbpedia.org/resource/Bruno_Fonseca",
        "predicate": "http://dbpedia.org/ontology/wikiPageWikiLink",
        "object": "http://dbpedia.org/resource/Category:20th-century_American_printmakers"
    },
    {
        "subject": "http://dbpedia.org/resource/Bruno_Fonseca",
        "predicate": "http://dbpedia.org/ontology/wikiPageWikiLink",
        "object": "http://dbpedia.org/resource/Charles_Cowles_(art_dealer)"
    },
    {
        "subject": "http://dbpedia.org/resource/Bruno_Fonseca",
        "predicate": "http://dbpedia.org/ontology/wikiPageWikiLink",
        "object": "http://dbpedia.org/resource/Pietrasanta"
    },
    {
        "subject": "http://dbpedia.org/resource/Bruno_Fonseca",
        "predicate": "http://dbpedia.org/ontology/wikiPageWikiLink",
        "object": "http://dbpedia.org/resource/Institut_Valenci\u00e0_d'Art_Modern"
    },
    {
        "subject": "http://dbpedia.org/resource/Bruno_Fonseca",
        "predicate": "http://dbpedia.org/ontology/wikiPageWikiLink",
        "object": "http://dbpedia.org/resource/New_York_City"
    },
    {
        "subject": "http://dbpedia.org/resource/Bruno_Fonseca",
        "predicate": "http://dbpedia.org/ontology/wikiPageWikiLink",
        "object": "http://dbpedia.org/resource/West_Village"
    },
    {
        "subject": "http://dbpedia.org/resource/Bruno_Fonseca",
        "predicate": "http://dbpedia.org/ontology/wikiPageWikiLink",
        "object": "http://dbpedia.org/resource/Metropolitan_Museum"
    },
    {
        "subject": "http://dbpedia.org/resource/Bruno_Fonseca",
        "predicate": "http://dbpedia.org/ontology/wikiPageWikiLink",
        "object": "http://dbpedia.org/resource/Houston_Museum_of_Fine_Arts"
    },
    {
        "subject": "http://dbpedia.org/resource/Bruno_Fonseca",
        "predicate": "http://dbpedia.org/ontology/wikiPageWikiLink",
        "object": "http://dbpedia.org/resource/American_people"
    },
    {
        "subject": "http://dbpedia.org/resource/Bruno_Fonseca",
        "predicate": "http://dbpedia.org/ontology/wikiPageWikiLink",
        "object": "http://dbpedia.org/resource/Caio_Fonseca"
    },
    {
        "subject": "http://dbpedia.org/resource/Bruno_Fonseca",
        "predicate": "http://dbpedia.org/ontology/wikiPageWikiLink",
        "object": "http://dbpedia.org/resource/Carlos_A._Vegh"
    },
    {
        "subject": "http://dbpedia.org/resource/Bruno_Fonseca",
        "predicate": "http://dbpedia.org/ontology/wikiPageWikiLink",
        "object": "http://dbpedia.org/resource/Rodolfo_Gambini"
    },
    {
        "subject": "http://dbpedia.org/resource/Bruno_Fonseca",
        "predicate": "http://dbpedia.org/ontology/wikiPageWikiLink",
        "object": "http://dbpedia.org/resource/Rodrigo_Santiago"
    },
    {
        "subject": "http://dbpedia.org/resource/Bruno_Fonseca",
        "predicate": "http://dbpedia.org/ontology/wikiPageWikiLink",
        "object": "http://dbpedia.org/resource/Category:Lists_of_people_by_ethnicity"
    },
    {
        "subject": "http://dbpedia.org/resource/Bruno_Fonseca",
        "predicate": "http://dbpedia.org/ontology/wikiPageWikiLink",
        "object": "http://dbpedia.org/resource/Bob_Bradley"
    },
    {
        "subject": "http://dbpedia.org/resource/Bruno_Fonseca",
        "predicate": "http://dbpedia.org/ontology/wikiPageWikiLink",
        "object": "http://dbpedia.org/resource/Hugo_Fattoruso"
    },
    {
        "subject": "http://dbpedia.org/resource/Bruno_Fonseca",
        "predicate": "http://dbpedia.org/ontology/wikiPageWikiLink",
        "object": "http://dbpedia.org/resource/Jonathan_Del_Arco"
    },
    {
        "subject": "http://dbpedia.org/resource/Bruno_Fonseca",
        "predicate": "http://dbpedia.org/ontology/wikiPageWikiLink",
        "object": "http://dbpedia.org/resource/Jorge_Gestoso"
    },
    {
        "subject": "http://dbpedia.org/resource/Bruno_Fonseca",
        "predicate": "http://dbpedia.org/ontology/wikiPageWikiLink",
        "object": "http://dbpedia.org/resource/Jorge_Majfud"
    },
    {
        "subject": "http://dbpedia.org/resource/Bruno_Fonseca",
        "predicate": "http://dbpedia.org/ontology/wikiPageWikiLink",
        "object": "http://dbpedia.org/resource/Juan_Jos\u00e9_Calandria"
    },
    {
        "subject": "http://dbpedia.org/resource/Bruno_Fonseca",
        "predicate": "http://dbpedia.org/ontology/wikiPageWikiLink",
        "object": "http://dbpedia.org/resource/Pedro_Sevcec"
    },
    {
        "subject": "http://dbpedia.org/resource/Bruno_Fonseca",
        "predicate": "http://dbpedia.org/ontology/wikiPageWikiLink",
        "object": "http://dbpedia.org/resource/Pepe_Fern\u00e1ndez"
    },
    {
        "subject": "http://dbpedia.org/resource/Bruno_Fonseca",
        "predicate": "http://dbpedia.org/ontology/wikiPageWikiLink",
        "object": "http://dbpedia.org/resource/Ricardo_L\u00f3pez_(stalker)"
    },
    {
        "subject": "http://dbpedia.org/resource/Bruno_Fonseca",
        "predicate": "http://dbpedia.org/ontology/wikiPageWikiLink",
        "object": "http://dbpedia.org/resource/David_Cruz_Thayne"
    },
    {
        "subject": "http://dbpedia.org/resource/Bruno_Fonseca",
        "predicate": "http://dbpedia.org/ontology/wikiPageWikiLink",
        "object": "http://dbpedia.org/resource/Limp_Wrist"
    },
    {
        "subject": "http://dbpedia.org/resource/Bruno_Fonseca",
        "predicate": "http://dbpedia.org/ontology/wikiPageWikiLink",
        "object": "http://dbpedia.org/resource/Pedro_Piedrabuena"
    },
    {
        "subject": "http://dbpedia.org/resource/Bruno_Fonseca",
        "predicate": "http://dbpedia.org/ontology/wikiPageWikiLink",
        "object": "http://dbpedia.org/resource/Category:Lists_of_American_people_by_ethnic_or_national_origin"
    },
    {
        "subject": "http://dbpedia.org/resource/Bruno_Fonseca",
        "predicate": "http://dbpedia.org/ontology/wikiPageWikiLink",
        "object": "http://dbpedia.org/resource/George_Davidsohn"
    },
    {
        "subject": "http://dbpedia.org/resource/Bruno_Fonseca",
        "predicate": "http://dbpedia.org/ontology/wikiPageWikiLink",
        "object": "http://dbpedia.org/resource/Cobra_Starship"
    },
    {
        "subject": "http://dbpedia.org/resource/Bruno_Fonseca",
        "predicate": "http://dbpedia.org/ontology/wikiPageWikiLink",
        "object": "http://dbpedia.org/resource/Emir_Rodr\u00edguez_Monegal"
    },
    {
        "subject": "http://dbpedia.org/resource/Bruno_Fonseca",
        "predicate": "http://dbpedia.org/ontology/wikiPageWikiLink",
        "object": "http://dbpedia.org/resource/Enrique_Graf"
    },
    {
        "subject": "http://dbpedia.org/resource/Bruno_Fonseca",
        "predicate": "http://dbpedia.org/ontology/wikiPageWikiLink",
        "object": "http://dbpedia.org/resource/Gabe_Saporta"
    },
    {
        "subject": "http://dbpedia.org/resource/Bruno_Fonseca",
        "predicate": "http://dbpedia.org/ontology/wikiPageWikiLink",
        "object": "http://dbpedia.org/resource/Gabriel_Wilensky"
    },
    {
        "subject": "http://dbpedia.org/resource/Bruno_Fonseca",
        "predicate": "http://dbpedia.org/ontology/wikiPageWikiLink",
        "object": "http://dbpedia.org/resource/George_DelHoyo"
    },
    {
        "subject": "http://dbpedia.org/resource/Bruno_Fonseca",
        "predicate": "http://dbpedia.org/ontology/wikiPageWikiLink",
        "object": "http://dbpedia.org/resource/Gisele_Ben-Dor"
    },
    {
        "subject": "http://dbpedia.org/resource/Bruno_Fonseca",
        "predicate": "http://dbpedia.org/ontology/wikiPageWikiLink",
        "object": "http://dbpedia.org/resource/Montevideo"
    },
    {
        "subject": "http://dbpedia.org/resource/Bruno_Fonseca",
        "predicate": "http://dbpedia.org/ontology/wikiPageWikiLink",
        "object": "http://dbpedia.org/resource/Loop_quantum_gravity"
    },
    {
        "subject": "http://dbpedia.org/resource/Bruno_Fonseca",
        "predicate": "http://dbpedia.org/ontology/wikiPageWikiLink",
        "object": "http://dbpedia.org/resource/Luis_Camnitzer"
    },
    {
        "subject": "http://dbpedia.org/resource/Bruno_Fonseca",
        "predicate": "http://dbpedia.org/ontology/wikiPageWikiLink",
        "object": "http://dbpedia.org/resource/Major_League_Soccer"
    },
    {
        "subject": "http://dbpedia.org/resource/Bruno_Fonseca",
        "predicate": "http://dbpedia.org/ontology/wikiPageWikiLink",
        "object": "http://dbpedia.org/resource/Category:Uruguayan_diaspora"
    },
    {
        "subject": "http://dbpedia.org/resource/Bruno_Fonseca",
        "predicate": "http://dbpedia.org/ontology/wikiPageWikiLink",
        "object": "http://dbpedia.org/resource/Francisco_Fattoruso"
    },
    {
        "subject": "http://dbpedia.org/resource/Bruno_Fonseca",
        "predicate": "http://dbpedia.org/ontology/wikiPageWikiLink",
        "object": "http://dbpedia.org/resource/Jos\u00e9_L._Duomarco"
    },
    {
        "subject": "http://dbpedia.org/resource/Bruno_Fonseca",
        "predicate": "http://dbpedia.org/ontology/wikiPageWikiLink",
        "object": "http://dbpedia.org/resource/Jos\u00e9_Serebrier"
    },
    {
        "subject": "http://dbpedia.org/resource/Bruno_Fonseca",
        "predicate": "http://dbpedia.org/ontology/wikiPageWikiLink",
        "object": "http://dbpedia.org/resource/Bruno_Fonseca"
    },
    {
        "subject": "http://dbpedia.org/resource/Bruno_Fonseca",
        "predicate": "http://dbpedia.org/ontology/wikiPageWikiLink",
        "object": "http://dbpedia.org/resource/CNN"
    },
    {
        "subject": "http://dbpedia.org/resource/Bruno_Fonseca",
        "predicate": "http://dbpedia.org/ontology/wikiPageWikiLink",
        "object": "http://dbpedia.org/resource/Category:American_people_of_Uruguayan_descent"
    },
    {
        "subject": "http://dbpedia.org/resource/Bruno_Fonseca",
        "predicate": "http://dbpedia.org/ontology/wikiPageWikiLink",
        "object": "http://dbpedia.org/resource/Isabel_Fonseca"
    },
    {
        "subject": "http://dbpedia.org/resource/Bruno_Fonseca",
        "predicate": "http://dbpedia.org/ontology/wikiPageWikiLink",
        "object": "http://dbpedia.org/resource/Adrian_Vallarino"
    },
    {
        "subject": "http://dbpedia.org/resource/Bruno_Fonseca",
        "predicate": "http://dbpedia.org/ontology/wikiPageWikiLink",
        "object": "http://dbpedia.org/resource/Agust\u00edn_Viana"
    },
    {
        "subject": "http://dbpedia.org/resource/Bruno_Fonseca",
        "predicate": "http://dbpedia.org/ontology/wikiPageWikiLink",
        "object": "http://dbpedia.org/resource/Alejandro_V\u00e9gh_Villegas"
    },
    {
        "subject": "http://dbpedia.org/resource/Bruno_Fonseca",
        "predicate": "http://dbpedia.org/ontology/wikiPageWikiLink",
        "object": "http://dbpedia.org/resource/Alejandro_Zaffaroni"
    },
    {
        "subject": "http://dbpedia.org/resource/Bruno_Fonseca",
        "predicate": "http://dbpedia.org/ontology/wikiPageWikiLink",
        "object": "http://dbpedia.org/resource/ESPN"
    },
    {
        "subject": "http://dbpedia.org/resource/Bruno_Fonseca",
        "predicate": "http://dbpedia.org/ontology/wikiPageWikiLink",
        "object": "http://dbpedia.org/resource/Fede_\u00c1lvarez"
    },
    {
        "subject": "http://dbpedia.org/resource/Bruno_Fonseca",
        "predicate": "http://dbpedia.org/ontology/wikiPageWikiLink",
        "object": "http://dbpedia.org/resource/Fernando_Clavijo"
    },
    {
        "subject": "http://dbpedia.org/resource/Bruno_Fonseca",
        "predicate": "http://dbpedia.org/ontology/wikiPageWikiLink",
        "object": "http://dbpedia.org/resource/Fernando_Espuelas"
    },
    {
        "subject": "http://dbpedia.org/resource/Bruno_Fonseca",
        "predicate": "http://dbpedia.org/ontology/wikiPageWikiLink",
        "object": "http://dbpedia.org/resource/Daniel_Pontet"
    },
    {
        "subject": "http://dbpedia.org/resource/Bruno_Fonseca",
        "predicate": "http://dbpedia.org/ontology/wikiPageWikiLink",
        "object": "http://dbpedia.org/resource/Jorge_Ramos_(commentator)"
    },
    {
        "subject": "http://dbpedia.org/resource/Bruno_Fonseca",
        "predicate": "http://dbpedia.org/ontology/wikiPageWikiLink",
        "object": "http://dbpedia.org/resource/Lengua_Armada_Discos"
    },
    {
        "subject": "http://dbpedia.org/resource/Bruno_Fonseca",
        "predicate": "http://dbpedia.org/ontology/wikiPageWikiLink",
        "object": "http://dbpedia.org/resource/Los_Crudos"
    },
    {
        "subject": "http://dbpedia.org/resource/Bruno_Fonseca",
        "predicate": "http://dbpedia.org/ontology/wikiPageWikiLink",
        "object": "http://dbpedia.org/resource/Jacksonville_University"
    },
    {
        "subject": "http://dbpedia.org/resource/Bruno_Fonseca",
        "predicate": "http://dbpedia.org/ontology/wikiPageWikiLink",
        "object": "http://dbpedia.org/resource/Jaime_Carbonell"
    },
    {
        "subject": "http://dbpedia.org/resource/Bruno_Fonseca",
        "predicate": "http://dbpedia.org/ontology/wikiPageWikiLink",
        "object": "http://dbpedia.org/resource/The_Holocaust"
    },
    {
        "subject": "http://dbpedia.org/resource/Bruno_Fonseca",
        "predicate": "http://dbpedia.org/ontology/wikiPageWikiLink",
        "object": "http://dbpedia.org/resource/Jo_Mora"
    },
    {
        "subject": "http://dbpedia.org/resource/Bruno_Fonseca",
        "predicate": "http://dbpedia.org/ontology/wikiPageWikiLink",
        "object": "http://dbpedia.org/resource/Tab_Ramos"
    },
    {
        "subject": "http://dbpedia.org/resource/Bruno_Fonseca",
        "predicate": "http://dbpedia.org/ontology/wikiPageWikiLink",
        "object": "http://dbpedia.org/resource/Hiber_Conteris"
    },
    {
        "subject": "http://dbpedia.org/resource/Bruno_Fonseca",
        "predicate": "http://dbpedia.org/ontology/wikiPageWikiLink",
        "object": "http://dbpedia.org/resource/Miguel_Terekhov"
    },
    {
        "subject": "http://dbpedia.org/resource/Bruno_Fonseca",
        "predicate": "http://dbpedia.org/ontology/wikiPageWikiLink",
        "object": "http://dbpedia.org/resource/Uruguayan_American"
    },
    {
        "subject": "http://dbpedia.org/resource/Bruno_Fonseca",
        "predicate": "http://dbpedia.org/ontology/wikiPageWikiLink",
        "object": "http://dbpedia.org/resource/Martin_Sorrondeguy"
    },
    {
        "subject": "http://dbpedia.org/resource/Bruno_Fonseca",
        "predicate": "http://dbpedia.org/ontology/wikiPageWikiLink",
        "object": "http://dbpedia.org/resource/Ida_Vitale"
    },
    {
        "subject": "http://dbpedia.org/resource/Bruno_Fonseca",
        "predicate": "http://dbpedia.org/ontology/wikiPageWikiLink",
        "object": "http://dbpedia.org/resource/Midtown_(band)"
    },
    {
        "subject": "http://dbpedia.org/resource/Bruno_Fonseca",
        "predicate": "http://dbpedia.org/ontology/wikiPageWikiLink",
        "object": "http://dbpedia.org/resource/Natalia_Cigliuti"
    },
    {
        "subject": "http://dbpedia.org/resource/Bruno_Fonseca",
        "predicate": "http://dbpedia.org/ontology/wikiPageWikiLink",
        "object": "http://dbpedia.org/resource/New_England_Revolution"
    },
    {
        "subject": "http://dbpedia.org/resource/Bruno_Fonseca",
        "predicate": "http://dbpedia.org/ontology/wikiPageWikiLink",
        "object": "http://dbpedia.org/resource/Rafael_Vi\u00f1oly"
    },
    {
        "subject": "http://dbpedia.org/resource/Bruno_Fonseca",
        "predicate": "http://dbpedia.org/ontology/wikiPageWikiLink",
        "object": "http://dbpedia.org/resource/Sebasti\u00e1n_Guenzatti"
    }
]